{
  "type": "Program",
  "body": [
    {
      "type": "ImportDeclaration",
      "source": {
        "type": "Literal",
        "value": "react",
        "raw": "'react'",
        "loc": {
          "start": {
            "line": 1,
            "column": 23
          },
          "end": {
            "line": 1,
            "column": 30
          }
        }
      },
      "specifiers": [
        {
          "type": "ImportNamespaceSpecifier",
          "local": {
            "type": "Identifier",
            "name": "React",
            "loc": {
              "start": {
                "line": 1,
                "column": 12
              },
              "end": {
                "line": 1,
                "column": 17
              }
            }
          },
          "loc": {
            "start": {
              "line": 1,
              "column": 7
            },
            "end": {
              "line": 1,
              "column": 17
            }
          }
        }
      ],
      "importKind": "value",
      "assertions": [],
      "loc": {
        "start": {
          "line": 1,
          "column": 0
        },
        "end": {
          "line": 1,
          "column": 31
        }
      }
    },
    {
      "type": "ImportDeclaration",
      "source": {
        "type": "Literal",
        "value": "./style.css",
        "raw": "'./style.css'",
        "loc": {
          "start": {
            "line": 2,
            "column": 7
          },
          "end": {
            "line": 2,
            "column": 20
          }
        }
      },
      "specifiers": [],
      "importKind": "value",
      "assertions": [],
      "loc": {
        "start": {
          "line": 2,
          "column": 0
        },
        "end": {
          "line": 2,
          "column": 21
        }
      }
    },
    {
      "type": "ExportDefaultDeclaration",
      "declaration": {
        "type": "FunctionDeclaration",
        "id": {
          "type": "Identifier",
          "name": "App",
          "loc": {
            "start": {
              "line": 4,
              "column": 24
            },
            "end": {
              "line": 4,
              "column": 27
            }
          }
        },
        "generator": false,
        "expression": false,
        "async": false,
        "params": [],
        "body": {
          "type": "BlockStatement",
          "body": [
            {
              "type": "ReturnStatement",
              "argument": {
                "type": "JSXElement",
                "openingElement": {
                  "type": "JSXOpeningElement",
                  "selfClosing": false,
                  "name": {
                    "type": "JSXIdentifier",
                    "name": "div",
                    "loc": {
                      "start": {
                        "line": 6,
                        "column": 5
                      },
                      "end": {
                        "line": 6,
                        "column": 8
                      }
                    }
                  },
                  "attributes": [],
                  "loc": {
                    "start": {
                      "line": 6,
                      "column": 4
                    },
                    "end": {
                      "line": 6,
                      "column": 9
                    }
                  }
                },
                "closingElement": {
                  "type": "JSXClosingElement",
                  "name": {
                    "type": "JSXIdentifier",
                    "name": "div",
                    "loc": {
                      "start": {
                        "line": 9,
                        "column": 6
                      },
                      "end": {
                        "line": 9,
                        "column": 9
                      }
                    }
                  },
                  "loc": {
                    "start": {
                      "line": 9,
                      "column": 4
                    },
                    "end": {
                      "line": 9,
                      "column": 10
                    }
                  }
                },
                "children": [
                  {
                    "type": "JSXText",
                    "value": "\n      ",
                    "raw": "\n      ",
                    "loc": {
                      "start": {
                        "line": 6,
                        "column": 9
                      },
                      "end": {
                        "line": 7,
                        "column": 6
                      }
                    }
                  },
                  {
                    "type": "JSXElement",
                    "openingElement": {
                      "type": "JSXOpeningElement",
                      "selfClosing": false,
                      "name": {
                        "type": "JSXIdentifier",
                        "name": "h1",
                        "loc": {
                          "start": {
                            "line": 7,
                            "column": 7
                          },
                          "end": {
                            "line": 7,
                            "column": 9
                          }
                        }
                      },
                      "attributes": [],
                      "loc": {
                        "start": {
                          "line": 7,
                          "column": 6
                        },
                        "end": {
                          "line": 7,
                          "column": 10
                        }
                      }
                    },
                    "closingElement": {
                      "type": "JSXClosingElement",
                      "name": {
                        "type": "JSXIdentifier",
                        "name": "h1",
                        "loc": {
                          "start": {
                            "line": 7,
                            "column": 29
                          },
                          "end": {
                            "line": 7,
                            "column": 31
                          }
                        }
                      },
                      "loc": {
                        "start": {
                          "line": 7,
                          "column": 27
                        },
                        "end": {
                          "line": 7,
                          "column": 32
                        }
                      }
                    },
                    "children": [
                      {
                        "type": "JSXText",
                        "value": "Hello StackBlitz!",
                        "raw": "Hello StackBlitz!",
                        "loc": {
                          "start": {
                            "line": 7,
                            "column": 10
                          },
                          "end": {
                            "line": 7,
                            "column": 27
                          }
                        }
                      }
                    ],
                    "loc": {
                      "start": {
                        "line": 7,
                        "column": 6
                      },
                      "end": {
                        "line": 7,
                        "column": 32
                      }
                    }
                  },
                  {
                    "type": "JSXText",
                    "value": "\n      ",
                    "raw": "\n      ",
                    "loc": {
                      "start": {
                        "line": 7,
                        "column": 32
                      },
                      "end": {
                        "line": 8,
                        "column": 6
                      }
                    }
                  },
                  {
                    "type": "JSXElement",
                    "openingElement": {
                      "type": "JSXOpeningElement",
                      "selfClosing": false,
                      "name": {
                        "type": "JSXIdentifier",
                        "name": "p",
                        "loc": {
                          "start": {
                            "line": 8,
                            "column": 7
                          },
                          "end": {
                            "line": 8,
                            "column": 8
                          }
                        }
                      },
                      "attributes": [],
                      "loc": {
                        "start": {
                          "line": 8,
                          "column": 6
                        },
                        "end": {
                          "line": 8,
                          "column": 9
                        }
                      }
                    },
                    "closingElement": {
                      "type": "JSXClosingElement",
                      "name": {
                        "type": "JSXIdentifier",
                        "name": "p",
                        "loc": {
                          "start": {
                            "line": 8,
                            "column": 52
                          },
                          "end": {
                            "line": 8,
                            "column": 53
                          }
                        }
                      },
                      "loc": {
                        "start": {
                          "line": 8,
                          "column": 50
                        },
                        "end": {
                          "line": 8,
                          "column": 54
                        }
                      }
                    },
                    "children": [
                      {
                        "type": "JSXText",
                        "value": "Start editing to see some magic happen :)",
                        "raw": "Start editing to see some magic happen :)",
                        "loc": {
                          "start": {
                            "line": 8,
                            "column": 9
                          },
                          "end": {
                            "line": 8,
                            "column": 50
                          }
                        }
                      }
                    ],
                    "loc": {
                      "start": {
                        "line": 8,
                        "column": 6
                      },
                      "end": {
                        "line": 8,
                        "column": 54
                      }
                    }
                  },
                  {
                    "type": "JSXText",
                    "value": "\n    ",
                    "raw": "\n    ",
                    "loc": {
                      "start": {
                        "line": 8,
                        "column": 54
                      },
                      "end": {
                        "line": 9,
                        "column": 4
                      }
                    }
                  }
                ],
                "loc": {
                  "start": {
                    "line": 6,
                    "column": 4
                  },
                  "end": {
                    "line": 9,
                    "column": 10
                  }
                }
              },
              "loc": {
                "start": {
                  "line": 5,
                  "column": 2
                },
                "end": {
                  "line": 10,
                  "column": 4
                }
              }
            }
          ],
          "loc": {
            "start": {
              "line": 4,
              "column": 30
            },
            "end": {
              "line": 11,
              "column": 1
            }
          }
        },
        "loc": {
          "start": {
            "line": 4,
            "column": 15
          },
          "end": {
            "line": 11,
            "column": 1
          }
        }
      },
      "exportKind": "value",
      "loc": {
        "start": {
          "line": 4,
          "column": 0
        },
        "end": {
          "line": 11,
          "column": 1
        }
      }
    }
  ],
  "sourceType": "module",
  "loc": {
    "start": {
      "line": 1,
      "column": 0
    },
    "end": {
      "line": 12,
      "column": 0
    }
  },
  "tokens": [
    {
      "type": "Keyword",
      "value": "import",
      "range": [
        0,
        6
      ],
      "loc": {
        "start": {
          "line": 1,
          "column": 0
        },
        "end": {
          "line": 1,
          "column": 6
        }
      }
    },
    {
      "type": "Punctuator",
      "value": "*",
      "range": [
        7,
        8
      ],
      "loc": {
        "start": {
          "line": 1,
          "column": 7
        },
        "end": {
          "line": 1,
          "column": 8
        }
      }
    },
    {
      "type": "Identifier",
      "value": "as",
      "range": [
        9,
        11
      ],
      "loc": {
        "start": {
          "line": 1,
          "column": 9
        },
        "end": {
          "line": 1,
          "column": 11
        }
      }
    },
    {
      "type": "Identifier",
      "value": "React",
      "range": [
        12,
        17
      ],
      "loc": {
        "start": {
          "line": 1,
          "column": 12
        },
        "end": {
          "line": 1,
          "column": 17
        }
      }
    },
    {
      "type": "Identifier",
      "value": "from",
      "range": [
        18,
        22
      ],
      "loc": {
        "start": {
          "line": 1,
          "column": 18
        },
        "end": {
          "line": 1,
          "column": 22
        }
      }
    },
    {
      "type": "String",
      "value": "'react'",
      "range": [
        23,
        30
      ],
      "loc": {
        "start": {
          "line": 1,
          "column": 23
        },
        "end": {
          "line": 1,
          "column": 30
        }
      }
    },
    {
      "type": "Punctuator",
      "value": ";",
      "range": [
        30,
        31
      ],
      "loc": {
        "start": {
          "line": 1,
          "column": 30
        },
        "end": {
          "line": 1,
          "column": 31
        }
      }
    },
    {
      "type": "Keyword",
      "value": "import",
      "range": [
        32,
        38
      ],
      "loc": {
        "start": {
          "line": 2,
          "column": 0
        },
        "end": {
          "line": 2,
          "column": 6
        }
      }
    },
    {
      "type": "String",
      "value": "'./style.css'",
      "range": [
        39,
        52
      ],
      "loc": {
        "start": {
          "line": 2,
          "column": 7
        },
        "end": {
          "line": 2,
          "column": 20
        }
      }
    },
    {
      "type": "Punctuator",
      "value": ";",
      "range": [
        52,
        53
      ],
      "loc": {
        "start": {
          "line": 2,
          "column": 20
        },
        "end": {
          "line": 2,
          "column": 21
        }
      }
    },
    {
      "type": "Keyword",
      "value": "export",
      "range": [
        55,
        61
      ],
      "loc": {
        "start": {
          "line": 4,
          "column": 0
        },
        "end": {
          "line": 4,
          "column": 6
        }
      }
    },
    {
      "type": "Keyword",
      "value": "default",
      "range": [
        62,
        69
      ],
      "loc": {
        "start": {
          "line": 4,
          "column": 7
        },
        "end": {
          "line": 4,
          "column": 14
        }
      }
    },
    {
      "type": "Keyword",
      "value": "function",
      "range": [
        70,
        78
      ],
      "loc": {
        "start": {
          "line": 4,
          "column": 15
        },
        "end": {
          "line": 4,
          "column": 23
        }
      }
    },
    {
      "type": "Identifier",
      "value": "App",
      "range": [
        79,
        82
      ],
      "loc": {
        "start": {
          "line": 4,
          "column": 24
        },
        "end": {
          "line": 4,
          "column": 27
        }
      }
    },
    {
      "type": "Punctuator",
      "value": "(",
      "range": [
        82,
        83
      ],
      "loc": {
        "start": {
          "line": 4,
          "column": 27
        },
        "end": {
          "line": 4,
          "column": 28
        }
      }
    },
    {
      "type": "Punctuator",
      "value": ")",
      "range": [
        83,
        84
      ],
      "loc": {
        "start": {
          "line": 4,
          "column": 28
        },
        "end": {
          "line": 4,
          "column": 29
        }
      }
    },
    {
      "type": "Punctuator",
      "value": "{",
      "range": [
        85,
        86
      ],
      "loc": {
        "start": {
          "line": 4,
          "column": 30
        },
        "end": {
          "line": 4,
          "column": 31
        }
      }
    },
    {
      "type": "Keyword",
      "value": "return",
      "range": [
        89,
        95
      ],
      "loc": {
        "start": {
          "line": 5,
          "column": 2
        },
        "end": {
          "line": 5,
          "column": 8
        }
      }
    },
    {
      "type": "Punctuator",
      "value": "(",
      "range": [
        96,
        97
      ],
      "loc": {
        "start": {
          "line": 5,
          "column": 9
        },
        "end": {
          "line": 5,
          "column": 10
        }
      }
    },
    {
      "type": "Punctuator",
      "value": "<",
      "range": [
        102,
        103
      ],
      "loc": {
        "start": {
          "line": 6,
          "column": 4
        },
        "end": {
          "line": 6,
          "column": 5
        }
      }
    },
    {
      "type": "JSXIdentifier",
      "value": "div",
      "range": [
        103,
        106
      ],
      "loc": {
        "start": {
          "line": 6,
          "column": 5
        },
        "end": {
          "line": 6,
          "column": 8
        }
      }
    },
    {
      "type": "Punctuator",
      "value": ">",
      "range": [
        106,
        107
      ],
      "loc": {
        "start": {
          "line": 6,
          "column": 8
        },
        "end": {
          "line": 6,
          "column": 9
        }
      }
    },
    {
      "type": "JSXText",
      "value": "\n      ",
      "range": [
        107,
        114
      ],
      "loc": {
        "start": {
          "line": 6,
          "column": 9
        },
        "end": {
          "line": 7,
          "column": 6
        }
      }
    },
    {
      "type": "Punctuator",
      "value": "<",
      "range": [
        114,
        115
      ],
      "loc": {
        "start": {
          "line": 7,
          "column": 6
        },
        "end": {
          "line": 7,
          "column": 7
        }
      }
    },
    {
      "type": "JSXIdentifier",
      "value": "h1",
      "range": [
        115,
        117
      ],
      "loc": {
        "start": {
          "line": 7,
          "column": 7
        },
        "end": {
          "line": 7,
          "column": 9
        }
      }
    },
    {
      "type": "Punctuator",
      "value": ">",
      "range": [
        117,
        118
      ],
      "loc": {
        "start": {
          "line": 7,
          "column": 9
        },
        "end": {
          "line": 7,
          "column": 10
        }
      }
    },
    {
      "type": "JSXText",
      "value": "Hello StackBlitz!",
      "range": [
        118,
        135
      ],
      "loc": {
        "start": {
          "line": 7,
          "column": 10
        },
        "end": {
          "line": 7,
          "column": 27
        }
      }
    },
    {
      "type": "Punctuator",
      "value": "<",
      "range": [
        135,
        136
      ],
      "loc": {
        "start": {
          "line": 7,
          "column": 27
        },
        "end": {
          "line": 7,
          "column": 28
        }
      }
    },
    {
      "type": "Punctuator",
      "value": "/",
      "range": [
        136,
        137
      ],
      "loc": {
        "start": {
          "line": 7,
          "column": 28
        },
        "end": {
          "line": 7,
          "column": 29
        }
      }
    },
    {
      "type": "JSXIdentifier",
      "value": "h1",
      "range": [
        137,
        139
      ],
      "loc": {
        "start": {
          "line": 7,
          "column": 29
        },
        "end": {
          "line": 7,
          "column": 31
        }
      }
    },
    {
      "type": "Punctuator",
      "value": ">",
      "range": [
        139,
        140
      ],
      "loc": {
        "start": {
          "line": 7,
          "column": 31
        },
        "end": {
          "line": 7,
          "column": 32
        }
      }
    },
    {
      "type": "JSXText",
      "value": "\n      ",
      "range": [
        140,
        147
      ],
      "loc": {
        "start": {
          "line": 7,
          "column": 32
        },
        "end": {
          "line": 8,
          "column": 6
        }
      }
    },
    {
      "type": "Punctuator",
      "value": "<",
      "range": [
        147,
        148
      ],
      "loc": {
        "start": {
          "line": 8,
          "column": 6
        },
        "end": {
          "line": 8,
          "column": 7
        }
      }
    },
    {
      "type": "JSXIdentifier",
      "value": "p",
      "range": [
        148,
        149
      ],
      "loc": {
        "start": {
          "line": 8,
          "column": 7
        },
        "end": {
          "line": 8,
          "column": 8
        }
      }
    },
    {
      "type": "Punctuator",
      "value": ">",
      "range": [
        149,
        150
      ],
      "loc": {
        "start": {
          "line": 8,
          "column": 8
        },
        "end": {
          "line": 8,
          "column": 9
        }
      }
    },
    {
      "type": "JSXText",
      "value": "Start editing to see some magic happen :)",
      "range": [
        150,
        191
      ],
      "loc": {
        "start": {
          "line": 8,
          "column": 9
        },
        "end": {
          "line": 8,
          "column": 50
        }
      }
    },
    {
      "type": "Punctuator",
      "value": "<",
      "range": [
        191,
        192
      ],
      "loc": {
        "start": {
          "line": 8,
          "column": 50
        },
        "end": {
          "line": 8,
          "column": 51
        }
      }
    },
    {
      "type": "Punctuator",
      "value": "/",
      "range": [
        192,
        193
      ],
      "loc": {
        "start": {
          "line": 8,
          "column": 51
        },
        "end": {
          "line": 8,
          "column": 52
        }
      }
    },
    {
      "type": "JSXIdentifier",
      "value": "p",
      "range": [
        193,
        194
      ],
      "loc": {
        "start": {
          "line": 8,
          "column": 52
        },
        "end": {
          "line": 8,
          "column": 53
        }
      }
    },
    {
      "type": "Punctuator",
      "value": ">",
      "range": [
        194,
        195
      ],
      "loc": {
        "start": {
          "line": 8,
          "column": 53
        },
        "end": {
          "line": 8,
          "column": 54
        }
      }
    },
    {
      "type": "JSXText",
      "value": "\n    ",
      "range": [
        195,
        200
      ],
      "loc": {
        "start": {
          "line": 8,
          "column": 54
        },
        "end": {
          "line": 9,
          "column": 4
        }
      }
    },
    {
      "type": "Punctuator",
      "value": "<",
      "range": [
        200,
        201
      ],
      "loc": {
        "start": {
          "line": 9,
          "column": 4
        },
        "end": {
          "line": 9,
          "column": 5
        }
      }
    },
    {
      "type": "Punctuator",
      "value": "/",
      "range": [
        201,
        202
      ],
      "loc": {
        "start": {
          "line": 9,
          "column": 5
        },
        "end": {
          "line": 9,
          "column": 6
        }
      }
    },
    {
      "type": "JSXIdentifier",
      "value": "div",
      "range": [
        202,
        205
      ],
      "loc": {
        "start": {
          "line": 9,
          "column": 6
        },
        "end": {
          "line": 9,
          "column": 9
        }
      }
    },
    {
      "type": "Punctuator",
      "value": ">",
      "range": [
        205,
        206
      ],
      "loc": {
        "start": {
          "line": 9,
          "column": 9
        },
        "end": {
          "line": 9,
          "column": 10
        }
      }
    },
    {
      "type": "Punctuator",
      "value": ")",
      "range": [
        209,
        210
      ],
      "loc": {
        "start": {
          "line": 10,
          "column": 2
        },
        "end": {
          "line": 10,
          "column": 3
        }
      }
    },
    {
      "type": "Punctuator",
      "value": ";",
      "range": [
        210,
        211
      ],
      "loc": {
        "start": {
          "line": 10,
          "column": 3
        },
        "end": {
          "line": 10,
          "column": 4
        }
      }
    },
    {
      "type": "Punctuator",
      "value": "}",
      "range": [
        212,
        213
      ],
      "loc": {
        "start": {
          "line": 11,
          "column": 0
        },
        "end": {
          "line": 11,
          "column": 1
        }
      }
    }
  ]
}